{
  "version": 3,
  "middleware": {
    "/": {
      "files": [
        "server/edge-runtime-webpack.js",
        "server/src/middleware.js"
      ],
      "name": "src/middleware",
      "page": "/",
      "matchers": [
        {
          "regexp": "^(?:\\/(_next\\/data\\/[^/]{1,}))?(?:\\/((?!api|_next\\/static|_next\\/image|favicon.ico|public).*))(.json)?[\\/#\\?]?$",
          "originalSource": "/((?!api|_next/static|_next/image|favicon.ico|public).*)"
        }
      ],
      "wasm": [],
      "assets": [],
      "env": {
        "__NEXT_BUILD_ID": "QaJJurM-83YIoL-YeucOA",
        "NEXT_SERVER_ACTIONS_ENCRYPTION_KEY": "zP4tquNeQTWVw45s3LODTqwImk4nV9bLHj8WSJSJYHY=",
        "__NEXT_PREVIEW_MODE_ID": "e009ac6182571ef46952a78c6d0fa26a",
        "__NEXT_PREVIEW_MODE_ENCRYPTION_KEY": "902e2a76ea232eeb1cd431b3a8fad684b2f76e999a9a84f8743cbe04b369ff9d",
        "__NEXT_PREVIEW_MODE_SIGNING_KEY": "8523c8a24f22a35af24d9cd3f363cb65cbd2915b4135d8053df2279703c563a3"
      }
    }
  },
  "functions": {},
  "sortedMiddleware": [
    "/"
  ]
}